jupyterlab_close_all_tabs_extension/__init__.py
jupyterlab_close_all_tabs_extension/_version.py
jupyterlab_close_all_tabs_extension-0.6.7.data/data/share/jupyter/labextensions/jupyterlab_close_all_tabs_extension/package.json
jupyterlab_close_all_tabs_extension-0.6.7.data/data/share/jupyter/labextensions/jupyterlab_close_all_tabs_extension/static/509.c907cda3798be4100d42.js
jupyterlab_close_all_tabs_extension-0.6.7.data/data/share/jupyter/labextensions/jupyterlab_close_all_tabs_extension/static/728.5ff80abf9b1570b68a7f.js
jupyterlab_close_all_tabs_extension-0.6.7.data/data/share/jupyter/labextensions/jupyterlab_close_all_tabs_extension/static/remoteEntry.a5505beea980e7dbfb19.js
jupyterlab_close_all_tabs_extension-0.6.7.data/data/share/jupyter/labextensions/jupyterlab_close_all_tabs_extension/static/style.js
jupyterlab_close_all_tabs_extension-0.6.7.data/data/share/jupyter/labextensions/jupyterlab_close_all_tabs_extension/static/third-party-licenses.json
jupyterlab_close_all_tabs_extension-0.6.7.data/data/share/jupyter/labextensions/jupyterlab_close_all_tabs_extension/install.json
jupyterlab_close_all_tabs_extension-0.6.7.dist-info/METADATA
jupyterlab_close_all_tabs_extension-0.6.7.dist-info/WHEEL
jupyterlab_close_all_tabs_extension-0.6.7.dist-info/licenses/LICENSE
jupyterlab_close_all_tabs_extension-0.6.7.dist-info/RECORD
